Metadata-Version: 1.0
Name: dogpile.core
Version: 0.4.0
Summary: A 'dogpile' lock, typically used as a component of a larger caching solution
Home-page: http://bitbucket.org/zzzeek/dogpile.core
Author: Mike Bayer
Author-email: mike_mp@zzzcomputing.com
License: BSD
Keywords: caching
Platform: UNKNOWN
Classifier: Development Status :: 4 - Beta
Classifier: Intended Audience :: Developers
Classifier: License :: OSI Approved :: BSD License
Classifier: Programming Language :: Python
Classifier: Programming Language :: Python :: 3
